anytrack/anytracker.py
anytrack/background.py
anytrack/cli.py
anytrack/contours.py
anytrack/files.py
anytrack/helpers.py
anytrack/main.py
anytrack/overlay_tracks.py
anytrack/register.py
anytrack/roiselect.py
anytrack/trajectory.py
anytrack/video.py
anytrack/yaml_helpers.py
anytrack-1.0.22.dist-info/METADATA
anytrack-1.0.22.dist-info/WHEEL
anytrack-1.0.22.dist-info/entry_points.txt
anytrack-1.0.22.dist-info/top_level.txt
anytrack-1.0.22.dist-info/RECORD
