Metadata-Version: 2.1
Name: anytrack
Version: 1.0.22
Summary: Simple tracking script for arbitrary object tracking in videos.
Home-page: https://pypi.python.org/pypi/anytrack
Author: Dennis Goldschmidt
Author-email: dennis.goldschmidt@neuro.fchampalimaud.org
License: GPLv3
Keywords: tracking,data analysis,fly
Platform: LinuxUbuntu
Platform: MacOSX-HighSierra
Classifier: Development Status :: 1 - Planning
Classifier: Operating System :: MacOS :: MacOS X
Classifier: Topic :: Utilities
Classifier: License :: OSI Approved :: GNU General Public License v3 (GPLv3)
Classifier: Programming Language :: Python :: 3.6
Requires-Python: >=3.6
Requires-Dist: numpy
Requires-Dist: pyyaml
Requires-Dist: pandas
Requires-Dist: scipy
Requires-Dist: opencv-python
Requires-Dist: tqdm
Requires-Dist: PyInquirer
